vibes_eval/__init__.py
vibes_eval/freeform.py
vibes_eval/judge.py
vibes_eval/multiple_choice.py
vibes_eval/plots.py
vibes_eval/runner.py
vibes_eval/vibes_eval.py
vibes_eval-0.1.0.dist-info/METADATA
vibes_eval-0.1.0.dist-info/WHEEL
vibes_eval-0.1.0.dist-info/top_level.txt
vibes_eval-0.1.0.dist-info/RECORD
