Metadata-Version: 2.4
Name: vibes_eval
Version: 0.1.0
Summary: A library for visualizing model evaluation results
Author: VisEval Contributors
License: MIT
Project-URL: Homepage, https://github.com/nielsrolf/viseval
Project-URL: Bug Tracker, https://github.com/nielsrolf/viseval/issues
Classifier: Programming Language :: Python :: 3
Classifier: License :: OSI Approved :: MIT License
Classifier: Operating System :: OS Independent
Requires-Python: >=3.11
Requires-Dist: numpy
Requires-Dist: pandas
Requires-Dist: matplotlib
Requires-Dist: pyyaml
Requires-Dist: python-slugify
Requires-Dist: python-dotenv
Requires-Dist: cache_on_disk
Requires-Dist: tqdm>=4.67.1
Requires-Dist: openweights>=0.4.0
